pipeline_model/__init__.py
pipeline_model-1.0.11.dist-info/METADATA
pipeline_model-1.0.11.dist-info/RECORD
pipeline_model-1.0.11.dist-info/WHEEL
pipeline_model-1.0.11.dist-info/top_level.txt
tensorflow/__init__.py
tensorflow_serving/__init__.py
