Metadata-Version: 2.1
Name: pipeline-model
Version: 1.0.11
Summary: PipelineAI Model
Home-page: https://github.com/pipelineai/pip/
Author: Chris Fregly
Author-email: github@pipeline.ai
License: UNKNOWN
Platform: UNKNOWN
Requires-Dist: grpcio (>=1.0)
